kirodb/__init__.py
kirodb/asynckiro.py
kirodb/kiro.py
kirodb-0.2.1.dist-info/METADATA
kirodb-0.2.1.dist-info/WHEEL
kirodb-0.2.1.dist-info/top_level.txt
kirodb-0.2.1.dist-info/RECORD
