Metadata-Version: 2.1
Name: kirodb
Version: 0.2.1
Summary: DataBase with GitHub Repo
Home-page: https://kirodb.herokuapp.com/
Author: t1rxdqq
Author-email: danilmerkulov63@gmail.com
License: UNKNOWN
Project-URL: Bug Tracker, https://github.com/t1rxdqq/kirodb-pip/issues
Platform: UNKNOWN
Classifier: Programming Language :: Python :: 3
Classifier: License :: OSI Approved :: MIT License
Classifier: Operating System :: OS Independent
Requires-Python: >=3.6
